{
  "name": "scala",
  "argv": [
    "/opt/homebrew/Cellar/scala/3.7.2/libexec/libexec/scala-cli.jar",
    "--cli-default-scala-version",
    "3.7.2",
    "--repository",
    "file:///opt/homebrew/Cellar/scala/3.7.2/libexec/maven2",
    "--prog-name",
    "scala",
    "--skip-cli-updates",
    "bsp",
    "--json-options",
    "/Users/justus/Desktop/robot-camp-group/.scala-build/ide-options-v2.json",
    "--json-launcher-options",
    "/Users/justus/Desktop/robot-camp-group/.scala-build/ide-launcher-options.json",
    "--envs-file",
    "/Users/justus/Desktop/robot-camp-group/.scala-build/ide-envs.json",
    "/Users/justus/Desktop/robot-camp-group"
  ],
  "version": "1.8.4",
  "bspVersion": "2.1.1",
  "languages": [
    "scala",
    "java"
  ]
}